masterchicken/CSV.py
masterchicken/__init__.py
masterchicken/__main__.py
masterchicken/backrooms.py
masterchicken/csvreader.py
masterchicken/egg.py
masterchicken-0.0.6.dist-info/LICENSE.txt
masterchicken-0.0.6.dist-info/METADATA
masterchicken-0.0.6.dist-info/WHEEL
masterchicken-0.0.6.dist-info/top_level.txt
masterchicken-0.0.6.dist-info/RECORD
