Metadata-Version: 2.1
Name: masterchicken
Version: 0.0.6
Summary: Basic math calculation with a CSV advanced reader and writer
Home-page: https://organicchicken.netlify.app/
Author: PythonChicken123
Author-email: wave6013@hotmail.com
License: MIT
Project-URL: Bug Tracker, https://github.com/PythonChicken123/masterchicken/issues
Project-URL: Download, https://pypi.org/project/masterchicken/
Project-URL: License, https://github.com/PythonChicken123/masterchicken/blob/main/LICENSE
Project-URL: Source Code, https://github.com/PythonChicken123/masterchicken/
Keywords: python,chicken,egg,csv,math
Classifier: Development Status :: 5 - Production/Stable
Classifier: Intended Audience :: Developers
Classifier: Operating System :: Microsoft :: Windows
Classifier: Operating System :: Unix
Classifier: Operating System :: MacOS :: MacOS X
Classifier: License :: OSI Approved :: MIT License
Classifier: Programming Language :: Python :: 3
Classifier: Programming Language :: Python :: 3.9
Classifier: Programming Language :: Python :: 3.10
Classifier: Programming Language :: Python :: 3.11
Classifier: Programming Language :: Python :: 3.12
Requires-Python: >=3.9
License-File: LICENSE.txt
Requires-Dist: bottle-websocket
Requires-Dist: bottle
Requires-Dist: build
Requires-Dist: cmake
Requires-Dist: distlib
Requires-Dist: docutils
Requires-Dist: numpy
Requires-Dist: packaging
Requires-Dist: pandas
Requires-Dist: pyarrow
Requires-Dist: readme-renderer
Requires-Dist: setuptools
Requires-Dist: urllib3
Requires-Dist: wheel
